odoo/addons/purchase_packaging_report/README.rst
odoo/addons/purchase_packaging_report/__init__.py
odoo/addons/purchase_packaging_report/__manifest__.py
odoo/addons/purchase_packaging_report/i18n/es.po
odoo/addons/purchase_packaging_report/i18n/it.po
odoo/addons/purchase_packaging_report/i18n/purchase_packaging_report.pot
odoo/addons/purchase_packaging_report/readme/CONFIGURE.md
odoo/addons/purchase_packaging_report/readme/CONTRIBUTORS.md
odoo/addons/purchase_packaging_report/readme/DESCRIPTION.md
odoo/addons/purchase_packaging_report/readme/USAGE.md
odoo/addons/purchase_packaging_report/report/__init__.py
odoo/addons/purchase_packaging_report/report/purchase_order_templates.xml
odoo/addons/purchase_packaging_report/report/purchase_quotation_templates.xml
odoo/addons/purchase_packaging_report/report/purchase_report.py
odoo/addons/purchase_packaging_report/report/purchase_report_views.xml
odoo/addons/purchase_packaging_report/static/description/icon.png
odoo/addons/purchase_packaging_report/static/description/index.html
odoo/addons/purchase_packaging_report/tests/__init__.py
odoo/addons/purchase_packaging_report/tests/test_purchase_packaging_report.py
odoo_addon_purchase_packaging_report-18.0.1.0.0.2.dist-info/METADATA
odoo_addon_purchase_packaging_report-18.0.1.0.0.2.dist-info/WHEEL
odoo_addon_purchase_packaging_report-18.0.1.0.0.2.dist-info/top_level.txt
odoo_addon_purchase_packaging_report-18.0.1.0.0.2.dist-info/RECORD
