Metadata-Version: 2.1
Name: odoo-addon-purchase_packaging_report
Version: 18.0.1.0.0.2
Requires-Python: >=3.10
Requires-Dist: odoo==18.0.*
Summary: Packaging data in purchase reports
Home-page: https://github.com/OCA/purchase-reporting
License: LGPL-3
Author: Moduon, Odoo Community Association (OCA)
Author-email: support@odoo-community.org
Classifier: Programming Language :: Python
Classifier: Framework :: Odoo
Classifier: Framework :: Odoo :: 18.0
Classifier: License :: OSI Approved :: GNU Lesser General Public License v3 (LGPLv3)
Classifier: Development Status :: 3 - Alpha
